{"begin_at": "2021-05-18T18:15:05Z", "complete": false, "detailed_stats": false, "end_at": "2021-05-18T19:06:19Z", "finished": true, "forfeit": false, "id": 44236, "length": 3074, "map": {"id": 7, "image_url": "https://cdn.pandascore.co/images/csgo/map/image/7/Csgo_overpass.jpg", "name": "Overpass"}, "match": {"serie": {"begin_at": "2021-05-04T17:00:00Z", "description": null, "end_at": "2021-07-11T20:00:00Z", "full_name": "Advanced Europe season 37 2021", "id": 3591, "league_id": 4243, "modified_at": "2021-07-12T23:33:48Z", "name": "Advanced Europe", "season": "37", "slug": "cs-go-esea-advanced-europe-37-2021", "tier": "d", "winner_id": null, "winner_type": null, "year": 2021}, "league_id": 4243, "videogame_version": null, "winner": {"acronym": null, "id": 127496, "image_url": "https://cdn.pandascore.co/images/team/image/127496/sampi_s_transparent.png", "location": null, "modified_at": "2022-04-04T16:47:55Z", "name": "Sampi", "slug": "sampi"}, "detailed_stats": false, "rescheduled": false, "opponents": [{"opponent": {"acronym": null, "id": 127496, "image_url": "https://cdn.pandascore.co/images/team/image/127496/sampi_s_transparent.png", "location": null, "modified_at": "2022-04-04T16:47:55Z", "name": "Sampi", "slug": "sampi"}, "type": "Team"}, {"opponent": {"acronym": null, "id": 3253, "image_url": "https://cdn.pandascore.co/images/team/image/3253/600px-PENTA_Sports-logo-notext.png", "location": "DE", "modified_at": "2021-06-17T14:35:40Z", "name": "PENTA", "slug": "penta"}, "type": "Team"}], "streams_list": [{"embed_url": "https://player.twitch.tv/?channel=m1hazz", "language": "ru", "main": true, "official": true, "raw_url": "https://www.twitch.tv/m1hazz"}], "id": 593355, "match_type": "best_of", "serie_id": 3591, "original_scheduled_at": "2021-05-18T18:00:00Z", "draw": false, "modified_at": "2021-05-18T19:06:19Z", "status": "finished", "end_at": "2021-05-18T19:06:19Z", "live": {"opens_at": null, "supported": false, "url": null}, "league": {"id": 4243, "image_url": "https://cdn.pandascore.co/images/league/image/4243/798px-ESEA_banner.png", "modified_at": "2020-11-12T15:51:24Z", "name": "ESEA", "slug": "cs-go-esea", "url": "https://play.esea.net/"}, "results": [{"score": 1, "team_id": 127496}, {"score": 0, "team_id": 3253}], "number_of_games": 1, "slug": "sampi-vs-penta-2021-05-18", "streams": {"english": {"embed_url": null, "raw_url": null}, "official": {"embed_url": "https://player.twitch.tv/?channel=m1hazz", "raw_url": "https://www.twitch.tv/m1hazz"}, "russian": {"embed_url": "https://player.twitch.tv/?channel=m1hazz", "raw_url": "https://www.twitch.tv/m1hazz"}}, "game_advantage": null, "games": [{"begin_at": "2021-05-18T18:15:05Z", "complete": false, "detailed_stats": false, "end_at": "2021-05-18T19:06:19Z", "finished": true, "forfeit": false, "id": 44236, "length": 3074, "match_id": 593355, "position": 1, "status": "finished", "video_url": null, "winner": {"id": 127496, "type": "Team"}, "winner_type": "Team"}], "official_stream_url": "https://www.twitch.tv/m1hazz", "tournament": {"begin_at": "2021-05-04T17:00:00Z", "end_at": "2021-06-27T19:44:00Z", "id": 5998, "league_id": 4243, "live_supported": false, "modified_at": "2021-07-12T23:33:48Z", "name": "Regular season", "prizepool": null, "serie_id": 3591, "slug": "cs-go-esea-advanced-europe-37-2021-regular-season", "tier": "d", "winner_id": null, "winner_type": "Team"}, "begin_at": "2021-05-18T18:15:05Z", "winner_id": 127496, "videogame": {"id": 3, "name": "CS:GO", "slug": "cs-go"}, "name": "Sampi vs PENTA", "live_embed_url": "https://player.twitch.tv/?channel=m1hazz", "tournament_id": 5998, "scheduled_at": "2021-05-18T18:00:00Z", "forfeit": false}, "match_id": 593355, "players": null, "position": 1, "rounds": null, "rounds_score": [], "status": "finished", "teams": null, "video_url": null, "winner": {"id": 127496, "type": "Team"}, "winner_type": "Team"}