{"begin_at": "2021-06-21T16:02:05Z", "complete": false, "detailed_stats": false, "end_at": "2021-06-21T16:52:07Z", "finished": true, "forfeit": false, "id": 45079, "length": 3002, "map": {"id": 7, "image_url": "https://cdn.pandascore.co/images/csgo/map/image/7/Csgo_overpass.jpg", "name": "Overpass"}, "match": {"serie": {"begin_at": "2021-05-03T16:00:00Z", "description": null, "end_at": "2021-07-07T17:05:00Z", "full_name": "Ligaen season 17 2021", "id": 3601, "league_id": 4473, "modified_at": "2021-07-07T17:07:43Z", "name": "Ligaen", "season": "17", "slug": "cs-go-dust2-dk-ligaen-17-2021", "tier": "d", "winner_id": 128394, "winner_type": "Team", "year": 2021}, "league_id": 4473, "videogame_version": null, "winner": {"acronym": null, "id": 128341, "image_url": "https://cdn.pandascore.co/images/team/image/128341/1200px_astralis_logo.svg.png", "location": null, "modified_at": "2022-03-25T15:07:26Z", "name": "Astralis Talent", "slug": "astralis-talent"}, "detailed_stats": false, "rescheduled": true, "opponents": [{"opponent": {"acronym": null, "id": 126634, "image_url": "https://cdn.pandascore.co/images/team/image/126634/600px_agf_esport_logo.png", "location": null, "modified_at": "2022-02-24T20:04:54Z", "name": "AGF", "slug": "agf"}, "type": "Team"}, {"opponent": {"acronym": null, "id": 128341, "image_url": "https://cdn.pandascore.co/images/team/image/128341/1200px_astralis_logo.svg.png", "location": null, "modified_at": "2022-03-25T15:07:26Z", "name": "Astralis Talent", "slug": "astralis-talent"}, "type": "Team"}], "streams_list": [{"embed_url": "https://player.twitch.tv/?channel=dust2tv", "language": "en", "main": true, "official": true, "raw_url": "https://www.twitch.tv/dust2tv"}], "id": 595034, "match_type": "best_of", "serie_id": 3601, "original_scheduled_at": "2021-05-31T20:00:00Z", "draw": false, "modified_at": "2021-06-21T16:52:08Z", "status": "finished", "end_at": "2021-06-21T16:52:07Z", "live": {"opens_at": null, "supported": false, "url": null}, "league": {"id": 4473, "image_url": "https://cdn.pandascore.co/images/league/image/4473/600px-Dust2dk_Liga_Cup.png", "modified_at": "2020-09-28T09:38:12Z", "name": "Dust2.dk", "slug": "cs-go-dust2-dk", "url": null}, "results": [{"score": 0, "team_id": 126634}, {"score": 1, "team_id": 128341}], "number_of_games": 1, "slug": "agf-vs-astralis-talent-2021-05-31", "streams": {"english": {"embed_url": "https://player.twitch.tv/?channel=dust2tv", "raw_url": "https://www.twitch.tv/dust2tv"}, "official": {"embed_url": "https://player.twitch.tv/?channel=dust2tv", "raw_url": "https://www.twitch.tv/dust2tv"}, "russian": {"embed_url": null, "raw_url": null}}, "game_advantage": null, "games": [{"begin_at": "2021-06-21T16:02:05Z", "complete": false, "detailed_stats": false, "end_at": "2021-06-21T16:52:07Z", "finished": true, "forfeit": false, "id": 45079, "length": 3002, "match_id": 595034, "position": 1, "status": "finished", "video_url": null, "winner": {"id": 128341, "type": "Team"}, "winner_type": "Team"}], "official_stream_url": "https://www.twitch.tv/dust2tv", "tournament": {"begin_at": "2021-05-03T16:00:00Z", "end_at": "2021-06-21T18:59:00Z", "id": 6033, "league_id": 4473, "live_supported": false, "modified_at": "2022-01-08T08:16:12Z", "name": "Regular Season", "prizepool": null, "serie_id": 3601, "slug": "cs-go-dust2-dk-ligaen-17-2021-regular-season", "tier": "d", "winner_id": 3331, "winner_type": "Team"}, "begin_at": "2021-06-21T16:02:05Z", "winner_id": 128341, "videogame": {"id": 3, "name": "CS:GO", "slug": "cs-go"}, "name": "Week 5: AGF vs Astralis Talent", "live_embed_url": "https://player.twitch.tv/?channel=dust2tv", "tournament_id": 6033, "scheduled_at": "2021-06-21T16:00:00Z", "forfeit": false}, "match_id": 595034, "players": null, "position": 1, "rounds": null, "rounds_score": [], "status": "finished", "teams": null, "video_url": null, "winner": {"id": 128341, "type": "Team"}, "winner_type": "Team"}