{"begin_at": "2021-09-06T20:11:06Z", "complete": false, "detailed_stats": false, "end_at": "2021-09-06T21:06:11Z", "finished": true, "forfeit": false, "id": 52639, "length": 3304, "map": {"id": 2, "image_url": "https://cdn.pandascore.co/images/csgo/map/image/2/De_new_inferno.jpg", "name": "Inferno"}, "match": {"serie": {"begin_at": "2021-08-16T15:00:00Z", "description": null, "end_at": "2021-10-03T22:00:00Z", "full_name": "Season 9 2021", "id": 3880, "league_id": 4248, "modified_at": "2021-08-27T08:29:59Z", "name": null, "season": "9", "slug": "cs-go-finnish-esports-league-9-2020", "tier": "d", "winner_id": null, "winner_type": null, "year": 2021}, "league_id": 4248, "videogame_version": null, "winner": {"acronym": null, "id": 127757, "image_url": "https://cdn.pandascore.co/images/team/image/127757/visu_logo_rgb.png", "location": null, "modified_at": "2021-11-08T14:00:18Z", "name": "VISU", "slug": "visu"}, "detailed_stats": false, "rescheduled": false, "opponents": [{"opponent": {"acronym": null, "id": 127147, "image_url": "https://cdn.pandascore.co/images/team/image/127147/nyyrikki_logo.png", "location": null, "modified_at": "2021-11-15T15:24:55Z", "name": "NYYRIKKI", "slug": "nyyrikki"}, "type": "Team"}, {"opponent": {"acronym": null, "id": 127757, "image_url": "https://cdn.pandascore.co/images/team/image/127757/visu_logo_rgb.png", "location": null, "modified_at": "2021-11-08T14:00:18Z", "name": "VISU", "slug": "visu"}, "type": "Team"}], "streams_list": [{"embed_url": "https://player.twitch.tv/?channel=esportsfinland", "language": "fi", "main": true, "official": true, "raw_url": "https://www.twitch.tv/esportsfinland"}], "id": 605945, "match_type": "best_of", "serie_id": 3880, "original_scheduled_at": "2021-09-06T18:00:00Z", "draw": false, "modified_at": "2021-09-12T07:38:54Z", "status": "finished", "end_at": "2021-09-06T21:06:10Z", "live": {"opens_at": null, "supported": false, "url": null}, "league": {"id": 4248, "image_url": "https://cdn.pandascore.co/images/league/image/4248/600px-Elisa_Viihde_CSGO-liiga.png", "modified_at": "2019-10-06T16:37:31Z", "name": "Finnish Esports League", "slug": "cs-go-finnish-esports-league", "url": "https://fel.gg/"}, "results": [{"score": 1, "team_id": 127147}, {"score": 2, "team_id": 127757}], "number_of_games": 3, "slug": "nyyrikki-vs-visu-2021-09-06", "streams": {"english": {"embed_url": null, "raw_url": null}, "official": {"embed_url": "https://player.twitch.tv/?channel=esportsfinland", "raw_url": "https://www.twitch.tv/esportsfinland"}, "russian": {"embed_url": null, "raw_url": null}}, "game_advantage": null, "games": [{"begin_at": "2021-09-06T18:16:06Z", "complete": false, "detailed_stats": false, "end_at": "2021-09-06T19:00:00Z", "finished": true, "forfeit": false, "id": 52637, "length": 2634, "match_id": 605945, "position": 1, "status": "finished", "video_url": null, "winner": {"id": 127757, "type": "Team"}, "winner_type": "Team"}, {"begin_at": "2021-09-06T19:04:02Z", "complete": false, "detailed_stats": false, "end_at": "2021-09-06T20:00:39Z", "finished": true, "forfeit": false, "id": 52638, "length": 3396, "match_id": 605945, "position": 2, "status": "finished", "video_url": null, "winner": {"id": 127147, "type": "Team"}, "winner_type": "Team"}, {"begin_at": "2021-09-06T20:11:06Z", "complete": false, "detailed_stats": false, "end_at": "2021-09-06T21:06:11Z", "finished": true, "forfeit": false, "id": 52639, "length": 3304, "match_id": 605945, "position": 3, "status": "finished", "video_url": null, "winner": {"id": 127757, "type": "Team"}, "winner_type": "Team"}], "official_stream_url": "https://www.twitch.tv/esportsfinland", "tournament": {"begin_at": "2021-08-16T15:00:00Z", "end_at": "2021-10-03T22:00:00Z", "id": 6591, "league_id": 4248, "live_supported": false, "modified_at": "2021-08-27T08:29:59Z", "name": "Group Stage", "prizepool": null, "serie_id": 3880, "slug": "cs-go-finnish-esports-league-9-2020-group-stage", "tier": "d", "winner_id": null, "winner_type": "Team"}, "begin_at": "2021-09-06T18:16:06Z", "winner_id": 127757, "videogame": {"id": 3, "name": "CS:GO", "slug": "cs-go"}, "name": "Round 4: NYYRIKKI vs VISU", "live_embed_url": "https://player.twitch.tv/?channel=esportsfinland", "tournament_id": 6591, "scheduled_at": "2021-09-06T18:00:00Z", "forfeit": false}, "match_id": 605945, "players": null, "position": 3, "rounds": null, "rounds_score": [], "status": "finished", "teams": null, "video_url": null, "winner": {"id": 127757, "type": "Team"}, "winner_type": "Team"}