{"begin_at": null, "complete": true, "detailed_stats": false, "end_at": null, "finished": false, "forfeit": false, "id": 54286, "length": null, "map": {"id": 8, "image_url": "https://cdn.pandascore.co/images/csgo/map/image/8/Csgo_dust2.0.jpg", "name": "Dust2"}, "match": {"serie": {"begin_at": "2021-08-24T23:00:00Z", "description": null, "end_at": "2021-09-30T03:00:00Z", "full_name": "Season 5 2021", "id": 3939, "league_id": 4623, "modified_at": "2021-10-10T12:32:37Z", "name": null, "season": "Season 5", "slug": "cs-go-redzone-pro-season-5-2021", "tier": "d", "winner_id": 127009, "winner_type": "Team", "year": 2021}, "league_id": 4623, "videogame_version": null, "winner": null, "detailed_stats": false, "rescheduled": false, "opponents": [{"opponent": {"acronym": null, "id": 128380, "image_url": "https://cdn.pandascore.co/images/team/image/128380/bears_esports_csgo.png", "location": "BR", "modified_at": "2021-11-26T22:59:01Z", "name": "Bears", "slug": "bears-e-sports"}, "type": "Team"}, {"opponent": {"acronym": null, "id": 126714, "image_url": "https://cdn.pandascore.co/images/team/image/126714/furia_academy.png", "location": "BR", "modified_at": "2022-04-07T15:56:27Z", "name": "FURIA Academy", "slug": "furia-inagame-cs-go"}, "type": "Team"}], "streams_list": [{"embed_url": "https://player.twitch.tv/?channel=rzdeira", "language": "pt", "main": false, "official": false, "raw_url": "https://www.twitch.tv/rzdeira"}, {"embed_url": "https://player.twitch.tv/?channel=coliseumarena", "language": "en", "main": true, "official": true, "raw_url": "https://www.twitch.tv/coliseumarena"}], "id": 607631, "match_type": "best_of", "serie_id": 3939, "original_scheduled_at": "2021-09-17T18:00:00Z", "draw": false, "modified_at": "2021-09-17T18:26:48Z", "status": "canceled", "end_at": null, "live": {"opens_at": null, "supported": false, "url": null}, "league": {"id": 4623, "image_url": "https://cdn.pandascore.co/images/league/image/4623/600px-RedZone_PRO_League_Season_3.png", "modified_at": "2021-08-02T06:45:23Z", "name": "RedZone PRO", "slug": "cs-go-redzone-pro", "url": null}, "results": [{"score": 0, "team_id": 128380}, {"score": 0, "team_id": 126714}], "number_of_games": 3, "slug": "bears-2021-09-17", "streams": {"english": {"embed_url": "https://player.twitch.tv/?channel=coliseumarena", "raw_url": "https://www.twitch.tv/coliseumarena"}, "official": {"embed_url": "https://player.twitch.tv/?channel=coliseumarena", "raw_url": "https://www.twitch.tv/coliseumarena"}, "russian": {"embed_url": null, "raw_url": null}}, "game_advantage": null, "games": [{"begin_at": null, "complete": true, "detailed_stats": false, "end_at": null, "finished": false, "forfeit": false, "id": 54286, "length": null, "match_id": 607631, "position": 1, "status": "not_started", "video_url": null, "winner": {"id": null, "type": "Team"}, "winner_type": "Team"}, {"begin_at": null, "complete": true, "detailed_stats": false, "end_at": null, "finished": false, "forfeit": false, "id": 54287, "length": null, "match_id": 607631, "position": 2, "status": "not_started", "video_url": null, "winner": {"id": null, "type": "Team"}, "winner_type": "Team"}, {"begin_at": null, "complete": true, "detailed_stats": false, "end_at": null, "finished": false, "forfeit": false, "id": 54288, "length": null, "match_id": 607631, "position": 3, "status": "not_started", "video_url": null, "winner": {"id": null, "type": "Team"}, "winner_type": "Team"}], "official_stream_url": "https://www.twitch.tv/coliseumarena", "tournament": {"begin_at": "2021-09-08T23:00:00Z", "end_at": "2021-09-23T19:55:00Z", "id": 6704, "league_id": 4623, "live_supported": false, "modified_at": "2021-10-10T12:32:37Z", "name": "Group B", "prizepool": null, "serie_id": 3939, "slug": "cs-go-redzone-pro-season-5-2021-group-b", "tier": "d", "winner_id": null, "winner_type": "Team"}, "begin_at": null, "winner_id": null, "videogame": {"id": 3, "name": "CS:GO", "slug": "cs-go"}, "name": "Bears vs FURIA Academy", "live_embed_url": "https://player.twitch.tv/?channel=coliseumarena", "tournament_id": 6704, "scheduled_at": "2021-09-17T18:00:00Z", "forfeit": false}, "match_id": 607631, "players": null, "position": 1, "rounds": null, "rounds_score": [], "status": "not_started", "teams": null, "video_url": null, "winner": {"id": null, "type": "Team"}, "winner_type": "Team"}