{"begin_at": "2021-11-10T20:25:38Z", "complete": false, "detailed_stats": false, "end_at": "2021-11-10T21:13:15Z", "finished": true, "forfeit": false, "id": 57605, "length": 2857, "map": {"id": 7, "image_url": "https://cdn.pandascore.co/images/csgo/map/image/7/Csgo_overpass.jpg", "name": "Overpass"}, "match": {"serie": {"begin_at": "2021-10-24T14:30:00Z", "description": null, "end_at": "2021-12-19T17:25:00Z", "full_name": "Season 7 2021", "id": 4081, "league_id": 4478, "modified_at": "2021-12-19T17:47:02Z", "name": null, "season": "7", "slug": "cs-go-fragleague-7-2021", "tier": "d", "winner_id": 126375, "winner_type": "Team", "year": 2021}, "league_id": 4478, "videogame_version": null, "winner": {"acronym": null, "id": 126417, "image_url": "https://cdn.pandascore.co/images/team/image/126417/600px_lilmix_logo.png", "location": "SE", "modified_at": "2022-04-10T10:02:51Z", "name": "Lilmix", "slug": "lilmix"}, "detailed_stats": false, "rescheduled": true, "opponents": [{"opponent": {"acronym": null, "id": 126417, "image_url": "https://cdn.pandascore.co/images/team/image/126417/600px_lilmix_logo.png", "location": "SE", "modified_at": "2022-04-10T10:02:51Z", "name": "Lilmix", "slug": "lilmix"}, "type": "Team"}, {"opponent": {"acronym": null, "id": 128512, "image_url": "https://cdn.pandascore.co/images/team/image/128512/190px_wizard_esports_logo.png", "location": "NO", "modified_at": "2022-01-21T13:26:16Z", "name": "Wizard", "slug": "wizard-esports"}, "type": "Team"}], "streams_list": [{"embed_url": "https://player.twitch.tv/?channel=fragbite", "language": "sv", "main": true, "official": true, "raw_url": "https://www.twitch.tv/fragbite"}], "id": 610620, "match_type": "best_of", "serie_id": 4081, "original_scheduled_at": "2021-11-07T15:30:00Z", "draw": false, "modified_at": "2021-11-10T22:08:12Z", "status": "finished", "end_at": "2021-11-10T22:08:10Z", "live": {"opens_at": null, "supported": false, "url": null}, "league": {"id": 4478, "image_url": "https://cdn.pandascore.co/images/league/image/4478/menu_logo.png", "modified_at": "2020-10-10T19:01:48Z", "name": "Fragleague", "slug": "cs-go-fragleague", "url": "https://fragbite.se/fragleague"}, "results": [{"score": 2, "team_id": 126417}, {"score": 0, "team_id": 128512}], "number_of_games": 3, "slug": "lilmix-vs-wizard-2021-11-07", "streams": {"english": {"embed_url": null, "raw_url": null}, "official": {"embed_url": "https://player.twitch.tv/?channel=fragbite", "raw_url": "https://www.twitch.tv/fragbite"}, "russian": {"embed_url": null, "raw_url": null}}, "game_advantage": null, "games": [{"begin_at": "2021-11-10T20:25:38Z", "complete": false, "detailed_stats": false, "end_at": "2021-11-10T21:13:15Z", "finished": true, "forfeit": false, "id": 57605, "length": 2857, "match_id": 610620, "position": 1, "status": "finished", "video_url": null, "winner": {"id": 126417, "type": "Team"}, "winner_type": "Team"}, {"begin_at": "2021-11-10T21:20:43Z", "complete": false, "detailed_stats": false, "end_at": "2021-11-10T22:08:11Z", "finished": true, "forfeit": false, "id": 57606, "length": 2847, "match_id": 610620, "position": 2, "status": "finished", "video_url": null, "winner": {"id": 126417, "type": "Team"}, "winner_type": "Team"}], "official_stream_url": "https://www.twitch.tv/fragbite", "tournament": {"begin_at": "2021-10-24T14:30:00Z", "end_at": "2021-11-16T18:30:00Z", "id": 6971, "league_id": 4478, "live_supported": false, "modified_at": "2021-12-19T17:47:02Z", "name": "Group B", "prizepool": null, "serie_id": 4081, "slug": "cs-go-fragleague-7-2021-group-b", "tier": "d", "winner_id": null, "winner_type": "Team"}, "begin_at": "2021-11-10T20:25:38Z", "winner_id": 126417, "videogame": {"id": 3, "name": "CS:GO", "slug": "cs-go"}, "name": "Lilmix vs Wizard", "live_embed_url": "https://player.twitch.tv/?channel=fragbite", "tournament_id": 6971, "scheduled_at": "2021-11-10T20:00:00Z", "forfeit": false}, "match_id": 610620, "players": null, "position": 1, "rounds": null, "rounds_score": [], "status": "finished", "teams": null, "video_url": null, "winner": {"id": 126417, "type": "Team"}, "winner_type": "Team"}