{"begin_at": "2021-11-10T23:17:24Z", "complete": false, "detailed_stats": false, "end_at": "2021-11-11T00:06:19Z", "finished": true, "forfeit": false, "id": 58889, "length": 2935, "map": {"id": 6, "image_url": "https://cdn.pandascore.co/images/csgo/map/image/6/Nuke_csgo.jpg", "name": "Nuke"}, "match": {"serie": {"begin_at": "2021-10-26T20:00:00Z", "description": null, "end_at": "2021-11-11T01:03:00Z", "full_name": "Season 6 2021", "id": 4091, "league_id": 4623, "modified_at": "2021-11-11T01:16:19Z", "name": "Season 6", "season": "", "slug": "cs-go-redzone-pro-season-6-2021", "tier": "d", "winner_id": 126714, "winner_type": "Team", "year": 2021}, "league_id": 4623, "videogame_version": null, "winner": {"acronym": null, "id": 126714, "image_url": "https://cdn.pandascore.co/images/team/image/126714/furia_academy.png", "location": "BR", "modified_at": "2022-04-07T15:56:27Z", "name": "FURIA Academy", "slug": "furia-inagame-cs-go"}, "detailed_stats": false, "rescheduled": false, "opponents": [{"opponent": {"acronym": null, "id": 126714, "image_url": "https://cdn.pandascore.co/images/team/image/126714/furia_academy.png", "location": "BR", "modified_at": "2022-04-07T15:56:27Z", "name": "FURIA Academy", "slug": "furia-inagame-cs-go"}, "type": "Team"}, {"opponent": {"acronym": null, "id": 129673, "image_url": null, "location": "", "modified_at": "2022-01-12T17:44:24Z", "name": "ex-Cear\u00e1 eSports", "slug": "ex-ceara-esports"}, "type": "Team"}], "streams_list": [{"embed_url": "https://player.twitch.tv/?channel=coliseumarena", "language": "pt", "main": true, "official": true, "raw_url": "https://www.twitch.tv/coliseumarena"}], "id": 612054, "match_type": "best_of", "serie_id": 4091, "original_scheduled_at": "2021-11-10T23:00:00Z", "draw": false, "modified_at": "2021-11-11T01:03:16Z", "status": "finished", "end_at": "2021-11-11T01:03:14Z", "live": {"opens_at": null, "supported": false, "url": null}, "league": {"id": 4623, "image_url": "https://cdn.pandascore.co/images/league/image/4623/600px-RedZone_PRO_League_Season_3.png", "modified_at": "2021-08-02T06:45:23Z", "name": "RedZone PRO", "slug": "cs-go-redzone-pro", "url": null}, "results": [{"score": 2, "team_id": 126714}, {"score": 0, "team_id": 129673}], "number_of_games": 3, "slug": "furia-academy-vs-ex-ceara-esports-2021-11-11", "streams": {"english": {"embed_url": null, "raw_url": null}, "official": {"embed_url": "https://player.twitch.tv/?channel=coliseumarena", "raw_url": "https://www.twitch.tv/coliseumarena"}, "russian": {"embed_url": null, "raw_url": null}}, "game_advantage": null, "games": [{"begin_at": "2021-11-10T23:17:24Z", "complete": false, "detailed_stats": false, "end_at": "2021-11-11T00:06:19Z", "finished": true, "forfeit": false, "id": 58889, "length": 2935, "match_id": 612054, "position": 1, "status": "finished", "video_url": null, "winner": {"id": 126714, "type": "Team"}, "winner_type": "Team"}, {"begin_at": "2021-11-11T00:16:31Z", "complete": false, "detailed_stats": false, "end_at": "2021-11-11T01:03:15Z", "finished": true, "forfeit": false, "id": 58890, "length": 2803, "match_id": 612054, "position": 2, "status": "finished", "video_url": null, "winner": {"id": 126714, "type": "Team"}, "winner_type": "Team"}], "official_stream_url": "https://www.twitch.tv/coliseumarena", "tournament": {"begin_at": "2021-11-05T17:00:00Z", "end_at": "2021-11-11T01:03:00Z", "id": 7045, "league_id": 4623, "live_supported": false, "modified_at": "2021-11-11T01:16:19Z", "name": "Playoffs", "prizepool": null, "serie_id": 4091, "slug": "cs-go-redzone-pro-season-6-2021-playoffs", "tier": "d", "winner_id": 126714, "winner_type": "Team"}, "begin_at": "2021-11-10T23:17:24Z", "winner_id": 126714, "videogame": {"id": 3, "name": "CS:GO", "slug": "cs-go"}, "name": "Final: FURIA Academy vs ex-Cear\u00e1 eSports", "live_embed_url": "https://player.twitch.tv/?channel=coliseumarena", "tournament_id": 7045, "scheduled_at": "2021-11-10T23:00:00Z", "forfeit": false}, "match_id": 612054, "players": null, "position": 1, "rounds": null, "rounds_score": [], "status": "finished", "teams": null, "video_url": null, "winner": {"id": 126714, "type": "Team"}, "winner_type": "Team"}