{"begin_at": null, "complete": true, "detailed_stats": true, "end_at": null, "finished": false, "forfeit": false, "id": 62997, "length": null, "map": null, "match": {"serie": {"begin_at": "2021-11-14T23:00:00Z", "description": null, "end_at": "2022-03-06T12:53:00Z", "full_name": "Online Stage Winter 2021", "id": 4136, "league_id": 4372, "modified_at": "2022-03-06T13:01:48Z", "name": "Online Stage", "season": "Winter", "slug": "cs-go-elisa-invitational-online-stage-winter-2021", "tier": "c", "winner_id": 126288, "winner_type": "Team", "year": 2021}, "league_id": 4372, "videogame_version": null, "winner": null, "detailed_stats": true, "rescheduled": false, "opponents": [{"opponent": {"acronym": null, "id": 126544, "image_url": "https://cdn.pandascore.co/images/team/image/126544/10276.png", "location": "IL", "modified_at": "2022-04-12T06:10:31Z", "name": "Finest", "slug": "finest"}, "type": "Team"}, {"opponent": {"acronym": null, "id": 3394, "image_url": "https://cdn.pandascore.co/images/team/image/3394/SPROUT.png", "location": "DE", "modified_at": "2022-04-13T07:20:00Z", "name": "Sprout", "slug": "sprout"}, "type": "Team"}], "streams_list": [{"embed_url": "https://player.twitch.tv/?channel=elisaesports", "language": "en", "main": true, "official": true, "raw_url": "https://www.twitch.tv/elisaesports"}], "id": 618337, "match_type": "best_of", "serie_id": 4136, "original_scheduled_at": "2022-01-17T14:00:00Z", "draw": false, "modified_at": "2022-01-12T15:37:41Z", "status": "canceled", "end_at": null, "live": {"opens_at": null, "supported": false, "url": null}, "league": {"id": 4372, "image_url": "https://cdn.pandascore.co/images/league/image/4372/600px-Elisa_Invitational.png", "modified_at": "2021-05-01T19:14:42Z", "name": "Elisa Invitational", "slug": "cs-go-elisa-invitational", "url": "https://elisaesports.fi"}, "results": [{"score": 0, "team_id": 126544}, {"score": 0, "team_id": 3394}], "number_of_games": 3, "slug": "finest-2022-01-17", "streams": {"english": {"embed_url": "https://player.twitch.tv/?channel=elisaesports", "raw_url": "https://www.twitch.tv/elisaesports"}, "official": {"embed_url": "https://player.twitch.tv/?channel=elisaesports", "raw_url": "https://www.twitch.tv/elisaesports"}, "russian": {"embed_url": null, "raw_url": null}}, "game_advantage": null, "games": [{"begin_at": null, "complete": true, "detailed_stats": true, "end_at": null, "finished": false, "forfeit": false, "id": 62996, "length": null, "match_id": 618337, "position": 1, "status": "not_started", "video_url": null, "winner": {"id": null, "type": "Team"}, "winner_type": "Team"}, {"begin_at": null, "complete": true, "detailed_stats": true, "end_at": null, "finished": false, "forfeit": false, "id": 62997, "length": null, "match_id": 618337, "position": 2, "status": "not_started", "video_url": null, "winner": {"id": null, "type": "Team"}, "winner_type": "Team"}, {"begin_at": null, "complete": true, "detailed_stats": true, "end_at": null, "finished": false, "forfeit": false, "id": 62998, "length": null, "match_id": 618337, "position": 3, "status": "not_started", "video_url": null, "winner": {"id": null, "type": "Team"}, "winner_type": "Team"}], "official_stream_url": "https://www.twitch.tv/elisaesports", "tournament": {"begin_at": "2021-11-14T23:00:00Z", "end_at": "2021-12-19T20:05:00Z", "id": 7105, "league_id": 4372, "live_supported": false, "modified_at": "2022-03-06T13:01:48Z", "name": "Regional Swiss Stage", "prizepool": null, "serie_id": 4136, "slug": "cs-go-elisa-invitational-online-stage-winter-2021-regional-swiss-stage", "tier": "c", "winner_id": null, "winner_type": "Team"}, "begin_at": null, "winner_id": null, "videogame": {"id": 3, "name": "CS:GO", "slug": "cs-go"}, "name": "Finest vs Sprout", "live_embed_url": "https://player.twitch.tv/?channel=elisaesports", "tournament_id": 7105, "scheduled_at": "2022-01-17T14:00:00Z", "forfeit": false}, "match_id": 618337, "players": [], "position": 2, "rounds": [], "rounds_score": [], "status": "not_started", "teams": [], "video_url": null, "winner": {"id": null, "type": "Team"}, "winner_type": "Team"}