{"begin_at": "2022-03-30T19:19:41Z", "complete": false, "detailed_stats": false, "end_at": "2022-03-30T20:17:59Z", "finished": true, "forfeit": false, "id": 68817, "length": 3498, "map": {"id": 1, "image_url": "https://cdn.pandascore.co/images/csgo/map/image/1/Csgo_mirage.jpg", "name": "Mirage"}, "match": {"serie": {"begin_at": "2022-03-18T17:30:00Z", "description": null, "end_at": null, "full_name": "March 2022", "id": 4500, "league_id": 4554, "modified_at": "2022-03-18T15:09:35Z", "name": null, "season": "March", "slug": "cs-go-gamers-club-liga-serie-a-march-2022", "tier": "d", "winner_id": null, "winner_type": null, "year": 2022}, "league_id": 4554, "videogame_version": null, "winner": {"acronym": null, "id": 127009, "image_url": "https://cdn.pandascore.co/images/team/image/127009/t46776.png", "location": null, "modified_at": "2022-04-01T08:58:29Z", "name": "SWS", "slug": "sws-gaming"}, "detailed_stats": false, "rescheduled": false, "opponents": [{"opponent": {"acronym": null, "id": 127009, "image_url": "https://cdn.pandascore.co/images/team/image/127009/t46776.png", "location": null, "modified_at": "2022-04-01T08:58:29Z", "name": "SWS", "slug": "sws-gaming"}, "type": "Team"}, {"opponent": {"acronym": null, "id": 129374, "image_url": "https://cdn.pandascore.co/images/team/image/129374/119px_meta_gaming_2020_allmode.png", "location": "BR", "modified_at": "2022-04-01T08:58:28Z", "name": "Meta Gaming BR", "slug": "meta-gaming-br"}, "type": "Team"}], "streams_list": [{"embed_url": null, "language": "pt", "main": false, "official": false, "raw_url": "http://twitch.tv/cutzmeretz"}, {"embed_url": "https://player.twitch.tv/?channel=gamersclubcs", "language": "en", "main": true, "official": true, "raw_url": "https://www.twitch.tv/gamersclubcs"}], "id": 626695, "match_type": "best_of", "serie_id": 4500, "original_scheduled_at": "2022-03-30T18:00:00Z", "draw": false, "modified_at": "2022-03-30T21:14:19Z", "status": "finished", "end_at": "2022-03-30T21:14:18Z", "live": {"opens_at": null, "supported": false, "url": null}, "league": {"id": 4554, "image_url": "https://cdn.pandascore.co/images/league/image/4554/Liga_Gamers_Club_SSrie_A_logo.png", "modified_at": "2021-03-25T17:20:41Z", "name": "Gamers Club Liga S\u00e9rie A", "slug": "cs-go-gamers-club-liga-serie-a", "url": ""}, "results": [{"score": 2, "team_id": 127009}, {"score": 1, "team_id": 129374}], "number_of_games": 3, "slug": "sws-vs-meta-gaming-br-2022-03-30", "streams": {"english": {"embed_url": "https://player.twitch.tv/?channel=gamersclubcs", "raw_url": "https://www.twitch.tv/gamersclubcs"}, "official": {"embed_url": "https://player.twitch.tv/?channel=gamersclubcs", "raw_url": "https://www.twitch.tv/gamersclubcs"}, "russian": {"embed_url": null, "raw_url": null}}, "game_advantage": null, "games": [{"begin_at": "2022-03-30T18:15:23Z", "complete": false, "detailed_stats": false, "end_at": "2022-03-30T19:05:01Z", "finished": true, "forfeit": false, "id": 68816, "length": 2977, "match_id": 626695, "position": 1, "status": "finished", "video_url": null, "winner": {"id": 129374, "type": "Team"}, "winner_type": "Team"}, {"begin_at": "2022-03-30T19:19:41Z", "complete": false, "detailed_stats": false, "end_at": "2022-03-30T20:17:59Z", "finished": true, "forfeit": false, "id": 68817, "length": 3498, "match_id": 626695, "position": 2, "status": "finished", "video_url": null, "winner": {"id": 127009, "type": "Team"}, "winner_type": "Team"}, {"begin_at": "2022-03-30T20:30:28Z", "complete": false, "detailed_stats": false, "end_at": "2022-03-30T21:14:18Z", "finished": true, "forfeit": false, "id": 68818, "length": 2630, "match_id": 626695, "position": 3, "status": "finished", "video_url": null, "winner": {"id": 127009, "type": "Team"}, "winner_type": "Team"}], "official_stream_url": "https://www.twitch.tv/gamersclubcs", "tournament": {"begin_at": "2022-03-23T18:00:00Z", "end_at": "2022-03-31T01:35:00Z", "id": 7782, "league_id": 4554, "live_supported": false, "modified_at": "2022-04-03T21:48:29Z", "name": "Group B", "prizepool": null, "serie_id": 4500, "slug": "cs-go-gamers-club-liga-serie-a-march-2022-group-b", "tier": "d", "winner_id": null, "winner_type": "Team"}, "begin_at": "2022-03-30T18:15:23Z", "winner_id": 127009, "videogame": {"id": 3, "name": "CS:GO", "slug": "cs-go"}, "name": "SWS vs Meta Gaming BR", "live_embed_url": "https://player.twitch.tv/?channel=gamersclubcs", "tournament_id": 7782, "scheduled_at": "2022-03-30T18:00:00Z", "forfeit": false}, "match_id": 626695, "players": null, "position": 2, "rounds": null, "rounds_score": [], "status": "finished", "teams": null, "video_url": null, "winner": {"id": 127009, "type": "Team"}, "winner_type": "Team"}