{"begin_at": null, "complete": false, "detailed_stats": false, "end_at": null, "finished": true, "forfeit": false, "id": 68886, "length": null, "map": null, "match": {"serie_id": 4504, "winner": {"acronym": null, "id": 125742, "image_url": "https://cdn.pandascore.co/images/team/image/125742/clg.png", "location": "US", "modified_at": "2022-04-10T07:35:00Z", "name": "CLG Red", "slug": "clg-red"}, "live_embed_url": null, "league": {"id": 4243, "image_url": "https://cdn.pandascore.co/images/league/image/4243/798px-ESEA_banner.png", "modified_at": "2020-11-12T15:51:24Z", "name": "ESEA", "slug": "cs-go-esea", "url": "https://play.esea.net/"}, "live": {"opens_at": null, "supported": false, "url": null}, "scheduled_at": "2022-03-19T22:00:00Z", "videogame_version": null, "draw": false, "match_type": "best_of", "tournament": {"begin_at": "2022-03-19T22:00:00Z", "end_at": "2022-03-21T00:00:00Z", "id": 7791, "league_id": 4243, "live_supported": false, "modified_at": "2022-03-20T18:04:46Z", "name": "Playoffs", "prizepool": "1000 United States Dollar", "serie_id": 4504, "slug": "cs-go-esea-female-cash-cup-north-america-5-winter-2022-playoffs", "tier": "d", "winner_id": null, "winner_type": "Team"}, "streams": {"english": {"embed_url": null, "raw_url": null}, "official": {"embed_url": null, "raw_url": null}, "russian": {"embed_url": null, "raw_url": null}}, "id": 626750, "league_id": 4243, "games": [{"begin_at": null, "complete": false, "detailed_stats": false, "end_at": null, "finished": true, "forfeit": false, "id": 68885, "length": null, "match_id": 626750, "position": 1, "status": "finished", "video_url": null, "winner": {"id": 125742, "type": "Team"}, "winner_type": "Team"}, {"begin_at": null, "complete": false, "detailed_stats": false, "end_at": null, "finished": true, "forfeit": false, "id": 68886, "length": null, "match_id": 626750, "position": 2, "status": "finished", "video_url": null, "winner": {"id": 125742, "type": "Team"}, "winner_type": "Team"}], "number_of_games": 3, "rescheduled": false, "modified_at": "2022-03-20T09:46:30Z", "videogame": {"id": 3, "name": "CS:GO", "slug": "cs-go"}, "winner_id": 125742, "official_stream_url": null, "results": [{"score": 2, "team_id": 125742}, {"score": 0, "team_id": 130312}], "opponents": [{"opponent": {"acronym": null, "id": 125742, "image_url": "https://cdn.pandascore.co/images/team/image/125742/clg.png", "location": "US", "modified_at": "2022-04-10T07:35:00Z", "name": "CLG Red", "slug": "clg-red"}, "type": "Team"}, {"opponent": {"acronym": null, "id": 130312, "image_url": null, "location": "US", "modified_at": "2022-03-27T10:03:43Z", "name": "Hot Flash", "slug": "hot-flash"}, "type": "Team"}], "status": "finished", "end_at": null, "original_scheduled_at": "2022-03-19T22:00:00Z", "game_advantage": null, "detailed_stats": false, "serie": {"begin_at": "2022-03-19T22:00:00Z", "description": null, "end_at": "2022-03-21T00:00:00Z", "full_name": "Female Cash Cup: North America 5 Winter 2022", "id": 4504, "league_id": 4243, "modified_at": "2022-03-20T09:45:49Z", "name": "Female Cash Cup: North America", "season": "5 Winter", "slug": "cs-go-esea-female-cash-cup-north-america-5-winter-2022", "tier": "d", "winner_id": null, "winner_type": null, "year": 2022}, "begin_at": "2022-03-19T22:00:00Z", "tournament_id": 7791, "name": "Semifinal 1: CLG Red vs Hot Flash", "slug": "clg-red-vs-hot-flash-2022-03-19", "streams_list": [], "forfeit": false}, "match_id": 626750, "players": null, "position": 2, "rounds": null, "rounds_score": [], "status": "finished", "teams": null, "video_url": null, "winner": {"id": 125742, "type": "Team"}, "winner_type": "Team"}