{"begin_at": "2020-10-13T12:23:01Z", "complete": true, "detailed_stats": true, "end_at": "2020-10-13T12:59:35Z", "finished": true, "forfeit": true, "id": 29137, "length": 2194, "map": null, "match": {"serie": {"begin_at": "2020-10-13T12:00:00Z", "description": null, "end_at": "2020-10-24T22:00:00Z", "full_name": "New York Online: CIS 2020", "id": 3024, "league_id": 4161, "modified_at": "2020-10-25T19:34:13Z", "name": "New York Online: CIS", "season": null, "slug": "cs-go-iem-new-york-online-cis-2020", "tier": "a", "winner_id": 3288, "winner_type": "Team", "year": 2020}, "league_id": 4161, "videogame_version": null, "winner": {"acronym": null, "id": 3288, "image_url": "https://cdn.pandascore.co/images/team/image/3288/600px_virtus.pro_2019.png", "location": "RU", "modified_at": "2022-03-07T16:58:58Z", "name": "Virtus.pro", "slug": "virtus-pro-75b4744b-43d9-4ebd-a8dc-f1e0f9be69b3"}, "detailed_stats": true, "rescheduled": false, "opponents": [{"opponent": {"acronym": null, "id": 3288, "image_url": "https://cdn.pandascore.co/images/team/image/3288/600px_virtus.pro_2019.png", "location": "RU", "modified_at": "2022-03-07T16:58:58Z", "name": "Virtus.pro", "slug": "virtus-pro-75b4744b-43d9-4ebd-a8dc-f1e0f9be69b3"}, "type": "Team"}, {"opponent": {"acronym": null, "id": 127721, "image_url": "https://cdn.pandascore.co/images/team/image/127721/7244.png", "location": "KZ", "modified_at": "2022-04-12T06:10:26Z", "name": "K23", "slug": "k23"}, "type": "Team"}], "streams_list": [{"embed_url": "https://player.twitch.tv/?channel=csgomc_ru", "language": "ru", "main": false, "official": false, "raw_url": "https://www.twitch.tv/csgomc_ru"}, {"embed_url": "https://player.twitch.tv/?channel=esl_csgo", "language": "en", "main": false, "official": true, "raw_url": "https://www.twitch.tv/esl_csgo"}], "id": 572322, "match_type": "best_of", "serie_id": 3024, "original_scheduled_at": "2020-10-13T12:00:00Z", "draw": false, "modified_at": "2020-11-05T06:58:12Z", "status": "finished", "end_at": "2020-10-13T14:58:45Z", "live": {"opens_at": null, "supported": false, "url": null}, "league": {"id": 4161, "image_url": "https://cdn.pandascore.co/images/league/image/4161/500px-IEM_logo_2014.png", "modified_at": "2019-03-04T11:00:40Z", "name": "IEM", "slug": "cs-go-iem", "url": null}, "results": [{"score": 2, "team_id": 3288}, {"score": 1, "team_id": 127721}], "number_of_games": 3, "slug": "virtus-pro-vs-k23-2020-10-13", "streams": {"english": {"embed_url": "https://player.twitch.tv/?channel=esl_csgo", "raw_url": "https://www.twitch.tv/esl_csgo"}, "official": {"embed_url": "https://player.twitch.tv/?channel=esl_csgo", "raw_url": "https://www.twitch.tv/esl_csgo"}, "russian": {"embed_url": "https://player.twitch.tv/?channel=csgomc_ru", "raw_url": "https://www.twitch.tv/csgomc_ru"}}, "game_advantage": null, "games": [{"begin_at": "2020-10-13T12:23:01Z", "complete": true, "detailed_stats": true, "end_at": "2020-10-13T12:59:35Z", "finished": true, "forfeit": true, "id": 29137, "length": 2194, "match_id": 572322, "position": 1, "status": "finished", "video_url": null, "winner": {"id": 127721, "type": "Team"}, "winner_type": "Team"}, {"begin_at": "2020-10-13T12:59:44Z", "complete": true, "detailed_stats": true, "end_at": "2020-10-13T13:19:35Z", "finished": true, "forfeit": false, "id": 29138, "length": 1191, "match_id": 572322, "position": 2, "status": "finished", "video_url": null, "winner": {"id": 3288, "type": "Team"}, "winner_type": "Team"}, {"begin_at": "2020-10-13T13:34:38Z", "complete": true, "detailed_stats": true, "end_at": "2020-10-13T14:58:45Z", "finished": true, "forfeit": false, "id": 29139, "length": 5047, "match_id": 572322, "position": 3, "status": "finished", "video_url": "https://player.twitch.tv/?video=v769087488&autoplay=true&t=1h24m&parent=www.hltv.org", "winner": {"id": 3288, "type": "Team"}, "winner_type": "Team"}], "official_stream_url": "https://www.twitch.tv/esl_csgo", "tournament": {"begin_at": "2020-10-13T12:00:00Z", "end_at": "2020-10-21T15:00:00Z", "id": 4883, "league_id": 4161, "live_supported": false, "modified_at": "2020-09-30T16:01:17Z", "name": "Group A", "prizepool": null, "serie_id": 3024, "slug": "cs-go-iem-new-york-online-cis-2020-group-a", "tier": "a", "winner_id": null, "winner_type": "Team"}, "begin_at": "2020-10-13T12:12:00Z", "winner_id": 3288, "videogame": {"id": 3, "name": "CS:GO", "slug": "cs-go"}, "name": "Virtus.pro vs K23", "live_embed_url": "https://player.twitch.tv/?channel=esl_csgo", "tournament_id": 4883, "scheduled_at": "2020-10-13T12:00:00Z", "forfeit": false}, "match_id": 572322, "players": [], "position": 1, "rounds": [], "rounds_score": [{"score": 0, "team_id": 127721}, {"score": 0, "team_id": 3288}], "status": "finished", "teams": [{"acronym": null, "id": 3288, "image_url": "https://cdn.pandascore.co/images/team/image/3288/600px_virtus.pro_2019.png", "location": "RU", "modified_at": "2022-03-07T16:58:58Z", "name": "Virtus.pro", "slug": "virtus-pro-75b4744b-43d9-4ebd-a8dc-f1e0f9be69b3"}, {"acronym": null, "id": 127721, "image_url": "https://cdn.pandascore.co/images/team/image/127721/7244.png", "location": "KZ", "modified_at": "2022-04-12T06:10:26Z", "name": "K23", "slug": "k23"}], "video_url": null, "winner": {"id": 127721, "type": "Team"}, "winner_type": "Team"}