{"begin_at": "2021-10-31T19:21:49Z", "complete": false, "detailed_stats": false, "end_at": "2021-10-31T20:12:32Z", "finished": true, "forfeit": false, "id": 57599, "length": 3042, "map": {"id": 20, "image_url": "https://cdn.pandascore.co/images/csgo/map/image/20/Vertigo.png", "name": "Vertigo"}, "match": {"serie_id": 4081, "winner": {"acronym": null, "id": 128684, "image_url": "https://cdn.pandascore.co/images/team/image/128684/380px_dream_gaming.png", "location": "DK", "modified_at": "2022-04-12T13:42:22Z", "name": "DREAM", "slug": "dream-gaming"}, "live_embed_url": "https://player.twitch.tv/?channel=wizardggez", "league": {"id": 4478, "image_url": "https://cdn.pandascore.co/images/league/image/4478/menu_logo.png", "modified_at": "2020-10-10T19:01:48Z", "name": "Fragleague", "slug": "cs-go-fragleague", "url": "https://fragbite.se/fragleague"}, "live": {"opens_at": null, "supported": false, "url": null}, "scheduled_at": "2021-10-31T19:00:00Z", "videogame_version": null, "draw": false, "match_type": "best_of", "tournament": {"begin_at": "2021-10-24T14:30:00Z", "end_at": "2021-11-16T18:30:00Z", "id": 6971, "league_id": 4478, "live_supported": false, "modified_at": "2021-12-19T17:47:02Z", "name": "Group B", "prizepool": null, "serie_id": 4081, "slug": "cs-go-fragleague-7-2021-group-b", "tier": "d", "winner_id": null, "winner_type": "Team"}, "streams": {"english": {"embed_url": null, "raw_url": null}, "official": {"embed_url": "https://player.twitch.tv/?channel=wizardggez", "raw_url": "https://www.twitch.tv/wizardggez"}, "russian": {"embed_url": null, "raw_url": null}}, "id": 610618, "league_id": 4478, "games": [{"begin_at": "2021-10-31T19:21:49Z", "complete": false, "detailed_stats": false, "end_at": "2021-10-31T20:12:32Z", "finished": true, "forfeit": false, "id": 57599, "length": 3042, "match_id": 610618, "position": 1, "status": "finished", "video_url": null, "winner": {"id": 128684, "type": "Team"}, "winner_type": "Team"}, {"begin_at": "2021-10-31T20:22:48Z", "complete": false, "detailed_stats": false, "end_at": "2021-10-31T20:53:30Z", "finished": true, "forfeit": false, "id": 57600, "length": 1841, "match_id": 610618, "position": 2, "status": "finished", "video_url": null, "winner": {"id": 128684, "type": "Team"}, "winner_type": "Team"}], "number_of_games": 3, "rescheduled": true, "modified_at": "2021-10-31T20:53:30Z", "videogame": {"id": 3, "name": "CS:GO", "slug": "cs-go"}, "winner_id": 128684, "official_stream_url": "https://www.twitch.tv/wizardggez", "results": [{"score": 2, "team_id": 128684}, {"score": 0, "team_id": 128512}], "opponents": [{"opponent": {"acronym": null, "id": 128684, "image_url": "https://cdn.pandascore.co/images/team/image/128684/380px_dream_gaming.png", "location": "DK", "modified_at": "2022-04-12T13:42:22Z", "name": "DREAM", "slug": "dream-gaming"}, "type": "Team"}, {"opponent": {"acronym": null, "id": 128512, "image_url": "https://cdn.pandascore.co/images/team/image/128512/190px_wizard_esports_logo.png", "location": "NO", "modified_at": "2022-01-21T13:26:16Z", "name": "Wizard", "slug": "wizard-esports"}, "type": "Team"}], "status": "finished", "end_at": "2021-10-31T20:53:29Z", "original_scheduled_at": "2021-10-31T18:00:00Z", "game_advantage": null, "detailed_stats": false, "serie": {"begin_at": "2021-10-24T14:30:00Z", "description": null, "end_at": "2021-12-19T17:25:00Z", "full_name": "Season 7 2021", "id": 4081, "league_id": 4478, "modified_at": "2021-12-19T17:47:02Z", "name": null, "season": "7", "slug": "cs-go-fragleague-7-2021", "tier": "d", "winner_id": 126375, "winner_type": "Team", "year": 2021}, "begin_at": "2021-10-31T19:21:49Z", "tournament_id": 6971, "name": "DREAM vs Wizard", "slug": "dream-vs-wizard-2021-10-31", "streams_list": [{"embed_url": "https://player.twitch.tv/?channel=wizardggez", "language": "no", "main": true, "official": true, "raw_url": "https://www.twitch.tv/wizardggez"}], "forfeit": false}, "match_id": 610618, "players": null, "position": 1, "rounds": null, "rounds_score": [], "status": "finished", "teams": null, "video_url": null, "winner": {"id": 128684, "type": "Team"}, "winner_type": "Team"}