{"begin_at": "2021-12-23T12:06:41Z", "complete": false, "detailed_stats": false, "end_at": "2021-12-23T12:54:43Z", "finished": true, "forfeit": false, "id": 62021, "length": 2882, "map": {"id": 2, "image_url": "https://cdn.pandascore.co/images/csgo/map/image/2/De_new_inferno.jpg", "name": "Inferno"}, "match": {"serie": {"begin_at": "2021-12-18T10:10:00Z", "description": null, "end_at": "2022-01-16T00:00:00Z", "full_name": "2021", "id": 4225, "league_id": 4708, "modified_at": "2021-12-30T08:33:38Z", "name": null, "season": null, "slug": "cs-go-back-to-back-tournament-2021", "tier": "d", "winner_id": null, "winner_type": null, "year": 2021}, "league_id": 4708, "videogame_version": null, "winner": {"acronym": null, "id": 129463, "image_url": "https://cdn.pandascore.co/images/team/image/129463/1.png", "location": "GB", "modified_at": "2022-03-18T14:16:06Z", "name": "Coalesce", "slug": "coalesce"}, "detailed_stats": false, "rescheduled": true, "opponents": [{"opponent": {"acronym": null, "id": 129463, "image_url": "https://cdn.pandascore.co/images/team/image/129463/1.png", "location": "GB", "modified_at": "2022-03-18T14:16:06Z", "name": "Coalesce", "slug": "coalesce"}, "type": "Team"}, {"opponent": {"acronym": null, "id": 129531, "image_url": "https://cdn.pandascore.co/images/team/image/129531/112px_rezist_allmode.png", "location": null, "modified_at": "2021-12-21T01:49:53Z", "name": "REZIST", "slug": "rezist"}, "type": "Team"}], "streams_list": [{"embed_url": "https://player.twitch.tv/?channel=watchfultv", "language": "ru", "main": true, "official": true, "raw_url": "https://www.twitch.tv/watchfultv"}], "id": 615086, "match_type": "best_of", "serie_id": 4225, "original_scheduled_at": "2021-12-23T11:00:00Z", "draw": false, "modified_at": "2021-12-23T13:57:43Z", "status": "finished", "end_at": "2021-12-23T13:57:42Z", "live": {"opens_at": null, "supported": false, "url": null}, "league": {"id": 4708, "image_url": "https://cdn.pandascore.co/images/league/image/4708/900px-BACK_TO_BACK_Tournament_allmode.png", "modified_at": "2021-12-16T21:52:37Z", "name": "BACK TO BACK Tournament", "slug": "cs-go-back-to-back-tournament", "url": null}, "results": [{"score": 2, "team_id": 129463}, {"score": 0, "team_id": 129531}], "number_of_games": 3, "slug": "2021-12-23", "streams": {"english": {"embed_url": null, "raw_url": null}, "official": {"embed_url": "https://player.twitch.tv/?channel=watchfultv", "raw_url": "https://www.twitch.tv/watchfultv"}, "russian": {"embed_url": "https://player.twitch.tv/?channel=watchfultv", "raw_url": "https://www.twitch.tv/watchfultv"}}, "game_advantage": null, "games": [{"begin_at": "2021-12-23T12:06:41Z", "complete": false, "detailed_stats": false, "end_at": "2021-12-23T12:54:43Z", "finished": true, "forfeit": false, "id": 62021, "length": 2882, "match_id": 615086, "position": 1, "status": "finished", "video_url": null, "winner": {"id": 129463, "type": "Team"}, "winner_type": "Team"}, {"begin_at": "2021-12-23T13:07:11Z", "complete": false, "detailed_stats": false, "end_at": "2021-12-23T13:57:42Z", "finished": true, "forfeit": false, "id": 62022, "length": 3031, "match_id": 615086, "position": 2, "status": "finished", "video_url": null, "winner": {"id": 129463, "type": "Team"}, "winner_type": "Team"}], "official_stream_url": "https://www.twitch.tv/watchfultv", "tournament": {"begin_at": "2021-12-18T10:10:00Z", "end_at": "2021-12-24T20:57:00Z", "id": 7261, "league_id": 4708, "live_supported": false, "modified_at": "2021-12-30T08:33:38Z", "name": "Swiss stage", "prizepool": null, "serie_id": 4225, "slug": "cs-go-back-to-back-tournament-2021-swiss-stage", "tier": "d", "winner_id": null, "winner_type": "Team"}, "begin_at": "2021-12-23T12:06:39Z", "winner_id": 129463, "videogame": {"id": 3, "name": "CS:GO", "slug": "cs-go"}, "name": "Round 4: Coalesce vs REZIST", "live_embed_url": "https://player.twitch.tv/?channel=watchfultv", "tournament_id": 7261, "scheduled_at": "2021-12-23T12:00:00Z", "forfeit": false}, "match_id": 615086, "players": null, "position": 1, "rounds": null, "rounds_score": [], "status": "finished", "teams": null, "video_url": null, "winner": {"id": 129463, "type": "Team"}, "winner_type": "Team"}