{"begin_at": null, "complete": true, "detailed_stats": false, "end_at": null, "finished": false, "forfeit": false, "id": 63559, "length": null, "map": null, "match": {"serie": {"begin_at": "2022-01-18T22:00:00Z", "description": null, "end_at": "2022-01-31T23:15:00Z", "full_name": "Season 1 2022", "id": 4312, "league_id": 4623, "modified_at": "2022-02-02T10:11:30Z", "name": null, "season": "Season 1", "slug": "cs-go-redzone-pro-season-1-2022", "tier": "d", "winner_id": null, "winner_type": null, "year": 2022}, "league_id": 4623, "videogame_version": null, "winner": {"acronym": null, "id": 130217, "image_url": "https://cdn.pandascore.co/images/team/image/130217/600px_godsent_full_allmode.png", "location": "BR", "modified_at": "2022-01-22T11:56:06Z", "name": "GODSENT Academy", "slug": "godsent-academy"}, "detailed_stats": false, "rescheduled": false, "opponents": [{"opponent": {"acronym": null, "id": 127072, "image_url": null, "location": null, "modified_at": "2022-01-19T21:12:38Z", "name": "ex-INTZ", "slug": "ex-intz"}, "type": "Team"}, {"opponent": {"acronym": null, "id": 130217, "image_url": "https://cdn.pandascore.co/images/team/image/130217/600px_godsent_full_allmode.png", "location": "BR", "modified_at": "2022-01-22T11:56:06Z", "name": "GODSENT Academy", "slug": "godsent-academy"}, "type": "Team"}], "streams_list": [{"embed_url": "https://player.twitch.tv/?channel=coliseumarena", "language": "pt", "main": true, "official": true, "raw_url": "https://www.twitch.tv/coliseumarena"}], "id": 619243, "match_type": "best_of", "serie_id": 4312, "original_scheduled_at": "2022-01-19T23:00:00Z", "draw": false, "modified_at": "2022-01-19T23:39:19Z", "status": "canceled", "end_at": null, "live": {"opens_at": null, "supported": false, "url": null}, "league": {"id": 4623, "image_url": "https://cdn.pandascore.co/images/league/image/4623/600px-RedZone_PRO_League_Season_3.png", "modified_at": "2021-08-02T06:45:23Z", "name": "RedZone PRO", "slug": "cs-go-redzone-pro", "url": null}, "results": [{"score": 0, "team_id": 127072}, {"score": 0, "team_id": 130217}], "number_of_games": 3, "slug": "ex-intz-vs-godsent-academy-2022-01-20", "streams": {"english": {"embed_url": null, "raw_url": null}, "official": {"embed_url": "https://player.twitch.tv/?channel=coliseumarena", "raw_url": "https://www.twitch.tv/coliseumarena"}, "russian": {"embed_url": null, "raw_url": null}}, "game_advantage": null, "games": [{"begin_at": null, "complete": true, "detailed_stats": false, "end_at": null, "finished": false, "forfeit": false, "id": 63557, "length": null, "match_id": 619243, "position": 1, "status": "not_started", "video_url": null, "winner": {"id": null, "type": "Team"}, "winner_type": "Team"}, {"begin_at": null, "complete": true, "detailed_stats": false, "end_at": null, "finished": false, "forfeit": false, "id": 63558, "length": null, "match_id": 619243, "position": 2, "status": "not_started", "video_url": null, "winner": {"id": null, "type": "Team"}, "winner_type": "Team"}, {"begin_at": null, "complete": true, "detailed_stats": false, "end_at": null, "finished": false, "forfeit": false, "id": 63559, "length": null, "match_id": 619243, "position": 3, "status": "not_started", "video_url": null, "winner": {"id": null, "type": "Team"}, "winner_type": "Team"}], "official_stream_url": "https://www.twitch.tv/coliseumarena", "tournament": {"begin_at": "2022-01-18T22:00:00Z", "end_at": "2022-01-21T23:54:00Z", "id": 7405, "league_id": 4623, "live_supported": false, "modified_at": "2022-02-02T10:11:30Z", "name": "Group B", "prizepool": null, "serie_id": 4312, "slug": "cs-go-redzone-pro-season-1-2022-group-b", "tier": "d", "winner_id": null, "winner_type": "Team"}, "begin_at": null, "winner_id": 130217, "videogame": {"id": 3, "name": "CS:GO", "slug": "cs-go"}, "name": "ex-INTZ vs GODSENT Academy", "live_embed_url": "https://player.twitch.tv/?channel=coliseumarena", "tournament_id": 7405, "scheduled_at": "2022-01-19T23:00:00Z", "forfeit": true}, "match_id": 619243, "players": null, "position": 3, "rounds": null, "rounds_score": [], "status": "not_started", "teams": null, "video_url": null, "winner": {"id": null, "type": "Team"}, "winner_type": "Team"}