{"begin_at": "2022-03-02T19:10:44Z", "complete": false, "detailed_stats": false, "end_at": "2022-03-02T19:40:27Z", "finished": true, "forfeit": false, "id": 67088, "length": 1782, "map": {"id": 2, "image_url": "https://cdn.pandascore.co/images/csgo/map/image/2/De_new_inferno.jpg", "name": "Inferno"}, "match": {"serie_id": 4400, "winner": {"acronym": null, "id": 129494, "image_url": "https://cdn.pandascore.co/images/team/image/129494/logo_247x300.png", "location": "SE", "modified_at": "2022-04-10T10:02:53Z", "name": "Kappa Bar", "slug": "kappa-bar"}, "live_embed_url": "https://player.twitch.tv/?channel=elitseriencsgo", "league": {"id": 4272, "image_url": "https://cdn.pandascore.co/images/league/image/4272/Svenska_Elitserien_2018_Logo.png", "modified_at": "2019-12-05T10:21:28Z", "name": "Svenska Elitserien", "slug": "cs-go-svenska-elitserien", "url": null}, "live": {"opens_at": null, "supported": false, "url": null}, "scheduled_at": "2022-03-02T19:00:00Z", "videogame_version": null, "draw": false, "match_type": "best_of", "tournament": {"begin_at": "2022-02-15T18:00:00Z", "end_at": "2022-05-12T22:00:00Z", "id": 7566, "league_id": 4272, "live_supported": false, "modified_at": "2022-02-15T17:27:52Z", "name": "Online Stage", "prizepool": null, "serie_id": 4400, "slug": "cs-go-svenska-elitserien-spring-2022-online-stage", "tier": "d", "winner_id": null, "winner_type": "Team"}, "streams": {"english": {"embed_url": null, "raw_url": null}, "official": {"embed_url": "https://player.twitch.tv/?channel=elitseriencsgo", "raw_url": "https://www.twitch.tv/elitseriencsgo"}, "russian": {"embed_url": null, "raw_url": null}}, "id": 624489, "league_id": 4272, "games": [{"begin_at": "2022-03-02T19:10:44Z", "complete": false, "detailed_stats": false, "end_at": "2022-03-02T19:40:27Z", "finished": true, "forfeit": false, "id": 67088, "length": 1782, "match_id": 624489, "position": 1, "status": "finished", "video_url": null, "winner": {"id": 129494, "type": "Team"}, "winner_type": "Team"}], "number_of_games": 1, "rescheduled": false, "modified_at": "2022-03-02T19:40:27Z", "videogame": {"id": 3, "name": "CS:GO", "slug": "cs-go"}, "winner_id": 129494, "official_stream_url": "https://www.twitch.tv/elitseriencsgo", "results": [{"score": 0, "team_id": 129833}, {"score": 1, "team_id": 129494}], "opponents": [{"opponent": {"acronym": null, "id": 129833, "image_url": "https://cdn.pandascore.co/images/team/image/129833/173px_goodfellas_se_allmode.png", "location": "SE", "modified_at": "2022-04-05T12:29:22Z", "name": "Goodfellas", "slug": "goodfellas-cs-go"}, "type": "Team"}, {"opponent": {"acronym": null, "id": 129494, "image_url": "https://cdn.pandascore.co/images/team/image/129494/logo_247x300.png", "location": "SE", "modified_at": "2022-04-10T10:02:53Z", "name": "Kappa Bar", "slug": "kappa-bar"}, "type": "Team"}], "status": "finished", "end_at": "2022-03-02T19:40:26Z", "original_scheduled_at": "2022-03-02T19:00:00Z", "game_advantage": null, "detailed_stats": false, "serie": {"begin_at": "2022-02-15T18:00:00Z", "description": null, "end_at": "2022-05-12T22:00:00Z", "full_name": "Spring 2022", "id": 4400, "league_id": 4272, "modified_at": "2022-02-15T16:40:29Z", "name": "", "season": "Spring", "slug": "cs-go-svenska-elitserien-spring-2022", "tier": "d", "winner_id": null, "winner_type": null, "year": 2022}, "begin_at": "2022-03-02T19:10:44Z", "tournament_id": 7566, "name": "Goodfellas vs Kappa Bar", "slug": "goodfellas-vs-kappa-bar-2022-03-02", "streams_list": [{"embed_url": "https://player.twitch.tv/?channel=elitseriencsgo", "language": "sv", "main": true, "official": true, "raw_url": "https://www.twitch.tv/elitseriencsgo"}], "forfeit": false}, "match_id": 624489, "players": null, "position": 1, "rounds": null, "rounds_score": [], "status": "finished", "teams": null, "video_url": null, "winner": {"id": 129494, "type": "Team"}, "winner_type": "Team"}